forwardSolver/.env.template
forwardSolver/__init__.py
forwardSolver/config.ini
forwardSolver/forwardSolver_2D/FreeFemMetrics.edp
forwardSolver/forwardSolver_2D/R3000/geometry_R3000-001.edp
forwardSolver/forwardSolver_2D/R3000/modelsolver_R3000-001.edp
forwardSolver/forwardSolver_2D/adjoint_inverse.edp
forwardSolver/forwardSolver_2D/examples/breast_2d.edp
forwardSolver/forwardSolver_2D/examples/complex_PDE.edp
forwardSolver/forwardSolver_2D/examples/cylinders.edp
forwardSolver/forwardSolver_2D/examples/electrode_number_2d.edp
forwardSolver/forwardSolver_2D/examples/ground_planes.edp
forwardSolver/forwardSolver_2D/examples/high_contrast_problem.edp
forwardSolver/forwardSolver_2D/examples/high_contrast_problem.log
forwardSolver/forwardSolver_2D/examples/parallel_plate_conductive.edp
forwardSolver/forwardSolver_2D/model_solver/README.md
forwardSolver/forwardSolver_2D/model_solver/args.edp
forwardSolver/forwardSolver_2D/model_solver/args_P1000-001.edp
forwardSolver/forwardSolver_2D/model_solver/args_P1000-004.edp
forwardSolver/forwardSolver_2D/model_solver/args_P1000-006.edp
forwardSolver/forwardSolver_2D/model_solver/args_P1000-009.edp
forwardSolver/forwardSolver_2D/model_solver/args_P1000-00X.edp
forwardSolver/forwardSolver_2D/model_solver/args_P1000-014.edp
forwardSolver/forwardSolver_2D/model_solver/args_P3000-005.edp
forwardSolver/forwardSolver_2D/model_solver/geometry_P1000-001.edp
forwardSolver/forwardSolver_2D/model_solver/geometry_P1000-009.edp
forwardSolver/forwardSolver_2D/model_solver/geometry_P1000-00X.edp
forwardSolver/forwardSolver_2D/model_solver/geometry_P1000-014_2gnds.edp
forwardSolver/forwardSolver_2D/model_solver/geometry_P1000-014_4gnds.edp
forwardSolver/forwardSolver_2D/model_solver/geometry_P3000-005.edp
forwardSolver/forwardSolver_2D/model_solver/geometry_imported.edp
forwardSolver/forwardSolver_2D/model_solver/geometry_imported_3D.edp
forwardSolver/forwardSolver_2D/model_solver/material_conductivity.edp
forwardsolver-1.2.dist-info/METADATA
forwardsolver-1.2.dist-info/WHEEL
forwardsolver-1.2.dist-info/entry_points.txt
forwardsolver-1.2.dist-info/licenses/LICENSE
forwardsolver-1.2.dist-info/RECORD
