Metadata-Version: 2.1
Name: forwardSolver
Version: 1.2
Summary: Zedsen Forward Solver
Classifier: Programming Language :: Python :: 3
Classifier: Operating System :: OS Independent
Requires-Python: ==3.10.6
